Verilog_Simulation/06_encoder/encoder.v
module encoder (A,Y);

input   [7:0] A;
output  [2:0] Y;

`ifdef DATAFLOW_LEVEL1
assign Y[2] =   A[7] | A[6] | A[5] | A[4]                       ;
assign Y[1] =   A[7] | A[6]                 | A[3] | A[2]       ;
assign Y[0] =   A[7]        | A[5]          | A[3]       | A[1] ;

`elsif DATAFLOW_LEVEL2 
assign Y    =   (A == 8'b0000_0001) ? 3'b000 :
                (A == 8'b0000_0010) ? 3'b001 :
                (A == 8'b0000_0100) ? 3'b010 :
                (A == 8'b0000_1000) ? 3'b011 :
                (A == 8'b0001_0000) ? 3'b100 :
                (A == 8'b0010_0000) ? 3'b101 :
                (A == 8'b0100_0000) ? 3'b110 :
                (A == 8'b1000_0000) ? 3'b111 :  3'b000;

`elsif DATAFLOW_LEVEL3
//assign 으로 구동안시킴 -> reg로 지정
reg [2:0]   Y;

always @ (A)
begin
    case(A)
        8'b0000_0001 :
            Y <= 3'b000;
        8'b0000_0010 :
            Y <= 3'b001;
        8'b0000_0100 :
            Y <= 3'b010;
        8'b0000_1000 :
            Y <= 3'b011;
        8'b0001_0000 :
            Y <= 3'b100;
        8'b0010_0000 :
            Y <= 3'b101;
        8'b0100_0000 :
            Y <= 3'b110;
        8'b1000_0000 : 
            Y <= 3'b111;
    default :
            Y <= 3'b000;

    endcase
end
`endif

endmodule

Verilog_Simulation/06_encoder/encoder_test.v
module encoder_test(t1, t2);
output [7:0]   t1;
input  [2:0]   t2;

//output port reg type simulation
reg            t1;

initial begin
   t1 <= 8'b0000_0001;

   #100;
   t1 <= 8'b0000_0010;

   #100;
   t1 <= 8'b0000_0100;

   #100;
   t1 <= 8'b0000_1000;

   #100;
   t1 <= 8'b0001_0000;

   #100;
   t1 <= 8'b0010_0000;

   #100;
   t1 <= 8'b0100_0000;

   #100;
   t1 <= 8'b1000_0000;

   #100;
   $finish;
end

endmodule

Verilog_Simulation/06_encoder/tb_testbench.v
`timescale 1ns/1ps

//`define DATAFLOW_LEVEL1
//`define DATAFLOW_LEVEL2
`define DATAFLOW_LEVEL3

module tb_testbench; 

wire [7:0]  A;  //input
wire [2:0]  Y;  //output

encoder_test tester (.t1(A), .t2(Y));
//                     |       ^        
//                     V       |         
encoder         dut (.A(A), .Y(Y));

always @(A or Y)
begin
    #1;
    $display("%8b %3b",A,Y);
end

initial begin
    $dumpfile("tb_test_out.vcd");   //관찰한 결과 저장
    $dumpvars(0,dut);               //dut module 관찰
end

endmodule

Verilog_Simulation/06_encoder/tb_test_out.vcd
$date
	Thu Dec 30 13:11:05 2021
$end
$version
	Icarus Verilog
$end
$timescale
	1ps
$end
$scope module tb_testbench $end
$scope module dut $end
$var wire 8 ! A [7:0] $end
$var reg 3 " Y [2:0] $end
$upscope $end
$upscope $end
$enddefinitions $end
#0
$dumpvars
b0 "
b1 !
$end
#100000
b1 "
b10 !
#200000
b10 "
b100 !
#300000
b11 "
b1000 !
#400000
b100 "
b10000 !
#500000
b101 "
b100000 !
#600000
b110 "
b1000000 !
#700000
b111 "
b10000000 !
