Verilog_Simulation/14_fsm_rtl/LIGHT.v
`define S0 2'b00
`define S1 2'b01
`define S2 2'b10
`define S3 2'b11

`define G   2'b00
`define Y   2'b01
`define R   2'b10   

module LIGHT(   CLK, RESETB,
                TA, TB, 
                LA1, LA0,
                LB1, LB0
);

input CLK, RESETB, TA, TB;

output LA1;
output LA0;
wire   [1:0] LA;
assign LA1 = LA[1];
assign LA0 = LA[0];


output LB1;
output LB0;  // nbit data -> bus structure
wire   [1:0] LB;
assign LB1 = LB[1];
assign LB0 = LB[0];

//  state
reg     [1:0]   S;
reg     [1:0]   NEXT_S;     //  조건 유지

//  (1) next state generation
// assign NEXT_S[1] = S[1] ^ S[0];
// assign NEXT_S[0] = ( ~S[1] & ~S[0] & ~TA ) | ( S[1] & ~S[0] & ~TB );
always @ ( TA or TB or S )
        case ( S )
        `S0 :
            if( ~TA )
                NEXT_S  <= `S1;
            else
                NEXT_S  <= S;
        `S1 :
            NEXT_S  <= `S2;
        `S2 :
            if ( ~TB )
                NEXT_S  <= `S3;
            else  
                NEXT_S  <= S;
        `S3 :
            NEXT_S  <= `S0;
        
        endcase

//  (2) next state -> current state update, feedback 
always @( negedge RESETB or posedge CLK)
    if (~RESETB)             // when RESETB is 0, may be reset, synchronous system, asynchronous system.
        S <= 2'b00;
    else
        S <= NEXT_S;


//  (3) output stage, stable state start

/*
assign LA1 =  S[1];
assign LA0 = ~S[1] & S[0];
assign LB1 = ~S[1];
assign LB0 =  S[1] & S[0];
*/

assign LA = S == `S0 ? `G:
            S == `S1 ? `Y:
            S == `S2 ? `R:
            S == `S3 ? `R: `G;

assign LB = S == `S0 ? `R:
            S == `S1 ? `R:
            S == `S2 ? `G:
            S == `S3 ? `Y: `R;

endmodule

Verilog_Simulation/14_fsm_rtl/LIGHT_test.v
module LIGHT_test(t1, t2, t3, t4, p1, p2, p3, p4);
//     LA1  LA0  LB1 LB0   
input  p1,  p2,  p3, p4;

//     CLK RESET  TA  TB   
output   t1, t2,  t3, t4;   

reg t1, t2, t3, t4;

//clock generation
initial begin
   forever #50 t1 = ~t1;   //period 100 half period 50
end


initial begin
   t1 <= 1'b1;    // CLK 
   t2 <= 1'b1;    // RESETB

   t3 <= 1'b1;    // TA, 가로방향 ON (default)
   t4 <= 1'b0;    // TB

   #20;
   t2 <= 1'b0;    // triggering reset (active low)

   #100;
   t2 <= 1'b1;    // reset release, reset은 F/F만 초기화시킴

   #95;
   t4 <= 1'b1;    // TB
   
   #100;
   t3 <= 1'b0;    // TA is 0

   #300;
   t3 <= 1'b1;    // TA is 1 again, but TB is on
   t4 <= 1'b0;    // when TB is 0, horizontal load is active
   
   #300;
   t3 <= 1'b0;    // TA is deactive

   #100;
   $finish;
end

endmodule

// 각각 다 병렬적으로 실행. 모든 파일이 동시에 실행된다.

Verilog_Simulation/13_fsm_gate/tb_testbench.v
`timescale 1ns/1ps

module tb_testbench; 

wire clk, resetb;
wire ta, tb, la1, la0, lb1, lb0;   

LIGHT_test tester (.t1(clk), .t2(resetb), .t3(ta), .t4(tb), .p1(la1), .p2(la0), .p3(lb1), .p4(lb0));
//                   |              |         |         |       ^           ^         ^           ^   
//                   V              V         V         V       |           |         |           |  
LIGHT      dut (.CLK(clk), .RESETB(resetb), .TA(ta), .TB(tb), .LA1(la1), .LA0(la0), .LB1(lb1), .LB0(lb0));  

//  always는 관찰대상, 변화를 감지할 수 있음

always @(clk or resetb or ta or tb or la1 or la0 or lb1 or lb0 )

begin
    #1;
    $display("%b %b %b %b %b%b %b%b", clk, resetb, ta, tb, la1, la0, lb1, lb0);
end

initial begin
    $dumpfile("tb_test_out.vcd");   //관찰한 결과 저장
    $dumpvars(0,dut);               //dut module 관찰
end

endmodule

Verilog_Simulation/14_fsm_rtl/tb_test_out.vcd
$date
	Tue Jan 04 22:36:55 2022
$end
$version
	Icarus Verilog
$end
$timescale
	1ps
$end
$scope module tb_testbench $end
$scope module dut $end
$var wire 1 ! TB $end
$var wire 1 " TA $end
$var wire 1 # RESETB $end
$var wire 1 $ LB1 $end
$var wire 1 % LB0 $end
$var wire 2 & LB [1:0] $end
$var wire 1 ' LA1 $end
$var wire 1 ( LA0 $end
$var wire 2 ) LA [1:0] $end
$var wire 1 * CLK $end
$var reg 2 + NEXT_S [1:0] $end
$var reg 2 , S [1:0] $end
$upscope $end
$upscope $end
$enddefinitions $end
#0
$dumpvars
bx ,
bx +
1*
bx )
x(
x'
bx &
x%
x$
1#
1"
0!
$end
#20000
b0 +
0(
0'
0%
1$
b0 )
b10 &
b0 ,
0#
#50000
0*
#100000
1*
#120000
1#
#150000
0*
#200000
1*
#215000
1!
#250000
0*
#300000
1*
#315000
b1 +
0"
#350000
0*
#400000
b10 +
1(
b1 )
b1 ,
1*
#450000
0*
#500000
0(
1'
0$
b10 )
b0 &
b10 ,
1*
#550000
0*
#600000
1*
#615000
b11 +
0!
1"
#650000
0*
#700000
b0 +
1%
b1 &
b11 ,
1*
#750000
0*
#800000
0'
0%
1$
b0 )
b10 &
b0 ,
1*
#850000
0*
#900000
1*
#915000
b1 +
0"
#950000
0*
#1000000
b10 +
1(
b1 )
b1 ,
1*
