Verilog_Simulation/08_adder4bit/adder.v
module adder (A, B, Cin, S, Cout);

input   A, B, Cin;
output  S, Cout;

`ifdef DATAFLOW_LEVEL1
assign      S    =  A ^ B ^ Cin;
assign      Cout =  (A & B) | (A & Cin) | (B & Cin);

`elsif GATE_LEVEL 
xor x0(S, A, B, Cin);

wire w0, w1, w2;

and a0(w0, A, B);
and a1(w1, B, Cin);
and a2(w2, A, Cin);

or  o0(Cout, W0, w1, w2);

`elsif DATAFLOW_LEVEL3

end
`endif

endmodule

Verilog_Simulation/07_adder/adder_test.v
module adder_test(t1, t2, t3, p1, p2);

output t1, t2, t3;
input  p1, p2;

//output port reg type simulation
reg       t1, t2, t3;

initial begin
   t1 <= 1'b0; t2 <= 1'b0;  t3 <= 1'b0; 

   #100;
   t1 <= 1'b0; t2 <= 1'b0;  t3 <= 1'b1; 

   #100;
   t1 <= 1'b0; t2 <= 1'b1;  t3 <= 1'b0; 

   #100;
   t1 <= 1'b0; t2 <= 1'b1;  t3 <= 1'b1; 

   #100;
   t1 <= 1'b1; t2 <= 1'b0;  t3 <= 1'b0; 

   #100;
   t1 <= 1'b1; t2 <= 1'b0;  t3 <= 1'b1; 

   #100;
   t1 <= 1'b1; t2 <= 1'b1;  t3 <= 1'b0; 
   
   #100;
   t1 <= 1'b1; t2 <= 1'b1;  t3 <= 1'b1;

   #100;
   $finish;
end

endmodule

Verilog_Simulation/07_adder/tb_testbench.v
`timescale 1ns/1ps

`define GATE_LEVEL
//`define DATAFLOW_LEVEL1
//`define DATAFLOW_LEVEL2
//`define DATAFLOW_LEVEL3

module tb_testbench; 

wire A, B, CIN, S, COUT; 

adder_test tester (.t1(A), .t2(B), .t3(CIN), .p1(S), .p2(COUT));
//                     |       |       |          ^          ^
//                     V       V       V          |          |
adder         dut    (.A(A), .B(B), .Cin(CIN), .S(S), .Cout(COUT));

always @(A or B or CIN or S or COUT)
begin
    #1;
    $display("%b %b %b %b %b", A, B, CIN, S, COUT);
end

initial begin
    $dumpfile("tb_test_out.vcd");   //관찰한 결과 저장
    $dumpvars(0,dut);               //dut module 관찰
end

endmodule

Verilog_Simulation/07_adder/tb_test_out.vcd
$date
	Tue Dec 28 15:19:28 2021
$end
$version
	Icarus Verilog
$end
$timescale
	1ps
$end
$scope module tb_testbench $end
$scope module dut $end
$var wire 1 ! Cout $end
$var wire 1 " S $end
$var wire 1 # W0 $end
$var wire 1 $ w0 $end
$var wire 1 % w1 $end
$var wire 1 & w2 $end
$var wire 1 ' Cin $end
$var wire 1 ( B $end
$var wire 1 ) A $end
$upscope $end
$upscope $end
$enddefinitions $end
#0
$dumpvars
0)
0(
0'
0&
0%
0$
z#
0"
x!
$end
#100000
1"
1'
#200000
0'
1(
#300000
1!
1%
0"
1'
#400000
x!
0%
1"
0'
0(
1)
#500000
1!
1&
0"
1'
#600000
x!
0&
1$
0'
1(
#700000
1!
1&
1%
1"
1'
