Verilog_Simulation/12_ff/ff.v
module ff(CLK, D, Q, Qb);
input   CLK, D;     //input is wire type
output  Q, Qb;

reg Q;          //output is reg or wire type. 
assign Qb = ~Q;

//CLK is rising edge, level triggerd : latch (simulation error, design error)
always @ ( posedge CLK  /*or D  unwanted latch*/ )  
        Q <= D;     // Sampling D at CLK edge
    //  else
    //  Q <= Q;     //  preserve

endmodule

Verilog_Simulation/12_ff/ff_test.v
module ff_test(t1, t2, p);

input  p;
output t1, t2;    //CLK, d  generation

reg t1, t2;

//clock generation
initial begin
   forever #50 t1 = ~t1;   //period 100 half period 50
end


initial begin
   t1 = 1'b0;    // CLK initially zero

   t2 = 1'b0;    // D is zero
   
   #75;
   t2 = 1'b1;    // D is 1

   #85;
   t2 = 1'b0;    // D is 0

   #10;
   t2 = 1'b1;    // D is 1

   #35;
   t2 = 1'b0;    // D is 0

   #5;
   t2 = 1'b1;    // D is 1

   #100;
   $finish;
end

endmodule

// 각각 다 병렬적으로 실행. 모든 파일이 동시에 실행된다.

Verilog_Simulation/12_ff/tb_testbench.v
`timescale 1ns/1ps

module tb_testbench; 

wire clk, d,  Q;   // d : input  Q : output

ff_test tester (.t1(clk), .t2(d), .p(Q) );
//                    |        |       ^
//                    V        V       |
ff         dut (.CLK(clk), .D(d), .Q(Q), .Qb( ));   //  Qb is floating

//  always는 관찰대상, 변화를 감지할 수 있음

always @(clk or d or Q)
begin
    #1;
    $display("%b %b %b", clk, d, Q);
end

initial begin
    $dumpfile("tb_test_out.vcd");   //관찰한 결과 저장
    $dumpvars(0,dut);               //dut module 관찰
end

endmodule

Verilog_Simulation/12_ff/tb_test_out.vcd
$date
	Mon Jan 03 14:34:39 2022
$end
$version
	Icarus Verilog
$end
$timescale
	1ps
$end
$scope module tb_testbench $end
$scope module dut $end
$var wire 1 ! Qb $end
$var wire 1 " D $end
$var wire 1 # CLK $end
$var reg 1 $ Q $end
$upscope $end
$upscope $end
$enddefinitions $end
#0
$dumpvars
x$
0#
0"
x!
$end
#50000
1!
0$
1#
#75000
1"
#100000
0#
#150000
0!
1$
1#
#160000
0"
#170000
1"
#200000
0#
#205000
0"
#210000
1"
